modelpg/__init__.py
modelpg/GAN/__init__.py
modelpg/GAN/cyclegan.py
modelpg/Helper/__init__.py
modelpg/Helper/helperfn.py
modelpg/Transformer/__init__.py
modelpg/Transformer/transformer.py
TensorPG-0.0.3.dist-info/LICENSE
TensorPG-0.0.3.dist-info/METADATA
TensorPG-0.0.3.dist-info/WHEEL
TensorPG-0.0.3.dist-info/top_level.txt
TensorPG-0.0.3.dist-info/RECORD
