Metadata-Version: 2.1
Name: TensorPG
Version: 0.0.3
Summary: Various Deep Learning Models (tensorflow)
Home-page: https://github.com/Shivam-21-11/Tf-Model-Packages
Author: Shivam Singh
Author-email: Shivamsingh2111@gmail.com
License: MIT
Keywords: Machine Learning,Computer Vision,Generative adversarial networks,Deep Learning,Transformer,NLP
Classifier: Development Status :: 2 - Pre-Alpha
Classifier: License :: OSI Approved :: MIT License
Classifier: Programming Language :: Python :: 3.10
Classifier: Operating System :: OS Independent
License-File: LICENSE
Requires-Dist: tensorflow
Requires-Dist: numpy
Requires-Dist: keras
Requires-Dist: matplotlib
Requires-Dist: tensorflow-text
